asyncdataflow/__init__.py
asyncdataflow/dataflow.py
asyncdataflow/definition.py
asyncdataflow/dispatch.py
asyncdataflow/exceptions.py
asyncdataflow/executor.py
asyncdataflow/inspector.py
asyncdataflow/mapper.py
async_data_flow-0.0.1.dist-info/AUTHORS
async_data_flow-0.0.1.dist-info/LICENCE
async_data_flow-0.0.1.dist-info/METADATA
async_data_flow-0.0.1.dist-info/WHEEL
async_data_flow-0.0.1.dist-info/top_level.txt
async_data_flow-0.0.1.dist-info/RECORD
