Metadata-Version: 2.1
Name: async-data-flow
Version: 0.0.1
Summary: Asynchronous data flow
Home-page: https://github.com/tomaszkingukrol/async-data-flow
Author: Tomasz Król
Author-email: tomasz.kingu.krol@gmail.com
Maintainer: Tomasz Król
Maintainer-email: tomasz.kingu.krol@gmail.com
License: UNKNOWN
Project-URL: Bug Tracker, https://github.com/tomaszkingukrol/async-data-flow/issues
Platform: UNKNOWN
Classifier: Programming Language :: Python
Classifier: Programming Language :: Python :: 3
Classifier: Programming Language :: Python :: 3.6
Requires-Python: >=3.6
License-File: LICENCE
License-File: AUTHORS
